spark_jdbc_ingestor/__init__.py
spark_jdbc_ingestor/main.py
spark_jdbc_ingestor-1.0.1.dist-info/LICENSE
spark_jdbc_ingestor-1.0.1.dist-info/METADATA
spark_jdbc_ingestor-1.0.1.dist-info/WHEEL
spark_jdbc_ingestor-1.0.1.dist-info/top_level.txt
spark_jdbc_ingestor-1.0.1.dist-info/RECORD
