Metadata-Version: 2.1
Name: spark_jdbc_ingestor
Version: 1.0.1
Summary: A library to handle JDBC ingestion from a SQL database in a simple and efficient way.
Author-email: Eduardo Franceschi <eduardo.franceschi@databricks.com>
License: GNU GENERAL PUBLIC LICENSE
Project-URL: Homepage, https://github.com/efranceschi/spark-jdbc-ingestor
Keywords: spark,jdbc,ingestor,ingestion
Classifier: License :: OSI Approved :: MIT License
Classifier: Programming Language :: Python
Classifier: Programming Language :: Python :: 3
Requires-Python: >=3.7
License-File: LICENSE
